psforms/__init__.py
psforms/controls.py
psforms/exc.py
psforms/fields.py
psforms/form.py
psforms/resource.py
psforms/style.css
psforms/utils.py
psforms/validators.py
psforms/widgets.py
psforms-0.6.0.dist-info/LICENSE
psforms-0.6.0.dist-info/METADATA
psforms-0.6.0.dist-info/WHEEL
psforms-0.6.0.dist-info/top_level.txt
psforms-0.6.0.dist-info/RECORD
