Metadata-Version: 2.1
Name: psforms
Version: 0.6.0
Summary: Hassle free PySide forms.
Home-page: http://github.com/danbradham/psforms.git
Author: Dan Bradham
Author-email: danielbradham@gmail.com
License: MIT
Platform: UNKNOWN
Classifier: Development Status :: 3 - Alpha
Classifier: Intended Audience :: Developers
Classifier: License :: OSI Approved :: MIT License
Classifier: Natural Language :: English
Classifier: Operating System :: OS Independent
Classifier: Programming Language :: Python
Classifier: Programming Language :: Python :: 2
Requires-Dist: Qt.py
